.hgtags
setup.py
pypytools/__init__.py
pypytools/_fakecython.py
pypytools/cast.py
pypytools/codegen.py
pypytools/color.py
pypytools/jitview.py
pypytools/unroll.py
pypytools/util.py
pypytools.egg-info/PKG-INFO
pypytools.egg-info/SOURCES.txt
pypytools.egg-info/dependency_links.txt
pypytools.egg-info/requires.txt
pypytools.egg-info/top_level.txt
pypytools/compat/__init__.py
pypytools/compat/micronumpy/__init__.py
pypytools/compat/micronumpy/core.py
pypytools/compat/micronumpy/function_base.py
pypytools/compat/micronumpy/numerictypes.py
pypytools/gc/__init__.py
pypytools/gc/custom.py
pypytools/gc/multihook.py
pypytools/gc/uniform.py
pypytools/gc/testing/__init__.py
pypytools/gc/testing/test_custom.py
pypytools/gc/testing/test_fakegc.py
pypytools/gc/testing/test_multihook.py
pypytools/gc/testing/test_uniform.py
pypytools/pypylog/__init__.py
pypytools/pypylog/model.py
pypytools/pypylog/parse.py
pypytools/pypylog/view.py
pypytools/pypylog/testing/__init__.py
pypytools/pypylog/testing/test_model.py
pypytools/pypylog/testing/test_parse.py
pypytools/testing/__init__.py
pypytools/testing/test_cast.py
pypytools/testing/test_codegen.py
pypytools/testing/test_fakecython.py
pypytools/testing/test_micronumpy.py
pypytools/testing/test_unroll.py
pypytools/testing/test_util.py